context/__init__.py
context/admin.py
context/apps.py
context/lookups.py
context/models.py
context/tests.py
context/urls.py
context/views.py
context/build_files/LICENSE
context/build_files/MANIFEST.in
context/build_files/README.md
context/build_files/setup.py
context/fixtures/context-sourcenet_entities_and_relations.json
context/migrations/0001_initial.py
context/migrations/0002_work_log_worker.py
context/migrations/0003_auto_20190301_1905.py
context/migrations/0004_auto_20190305_1858.py
context/migrations/0005_auto_20190402_1913.py
context/migrations/0006_auto_20190419_1711.py
context/migrations/0007_auto_20190424_1833.py
context/migrations/0008_auto_20190425_0259.py
context/migrations/0009_auto_20190501_1607.py
context/migrations/0010_auto_20190501_2229.py
context/migrations/0011_auto_20190502_1537.py
context/migrations/0012_auto_20190502_1555.py
context/migrations/0013_entity_relation_relation_through.py
context/migrations/0014_auto_20190807_2005.py
context/migrations/0015_entity_relation_type_relation_through_entity_type.py
context/migrations/0016_auto_20190821_1820.py
context/migrations/0017_auto_20190821_1833.py
context/migrations/0018_auto_20190821_1835.py
context/migrations/0019_entity_entity_type.py
context/migrations/0020_auto_20190905_0230.py
context/migrations/0021_auto_20190905_0231.py
context/migrations/0022_auto_20190905_0236.py
context/migrations/0023_entity_trait_entity_type_trait.py
context/migrations/0024_auto_20190906_1918.py
context/migrations/__init__.py
context/shared/__init__.py
context/shared/context_base.py
context/shared/entity_models.py
context/shared/person_details.py
context/static/context/context.css
context/templates/context/base.html
context/templates/context/index.html
context/templates/registration/login.html
context/tests/__init__.py
context/tests/test_helper.py
context/tests/models/__init__.py
context/tests/models/test_Entity_Identifier_Type_model.py
context/tests/models/test_Entity_Identifier_model.py
django_context_core-1.0.1.post4.dist-info/LICENSE
django_context_core-1.0.1.post4.dist-info/METADATA
django_context_core-1.0.1.post4.dist-info/WHEEL
django_context_core-1.0.1.post4.dist-info/top_level.txt
django_context_core-1.0.1.post4.dist-info/RECORD
