Metadata-Version: 2.1
Name: django-context-core
Version: 1.0.1.post4
Summary: Generalized django application framework for tracking entities and traits of and relations between them.
Home-page: https://github.com/jonathanmorgan/context
Author: Jonathan Morgan
Author-email: jonathan.morgan.007@gmail.com
License: UNKNOWN
Platform: UNKNOWN
Classifier: Programming Language :: Python :: 3
Classifier: License :: OSI Approved :: GNU Lesser General Public License v3 or later (LGPLv3+)
Classifier: Operating System :: OS Independent
Classifier: Development Status :: 4 - Beta
Classifier: Framework :: Django
Classifier: Intended Audience :: Developers
Classifier: Intended Audience :: Science/Research
Classifier: Topic :: Utilities
Requires-Python: >=3.6
Requires-Dist: django
Requires-Dist: django-ajax-selects
Requires-Dist: django-basic-config
Requires-Dist: django-json-widget
Requires-Dist: django-taggit
Requires-Dist: psycopg2
Requires-Dist: python-utilities-jsm
